HttpRetry/__init__.py
HttpRetry/main.py
httpretry-0.1.0.dist-info/LICENSE
httpretry-0.1.0.dist-info/METADATA
httpretry-0.1.0.dist-info/WHEEL
httpretry-0.1.0.dist-info/RECORD
