Metadata-Version: 2.3
Name: HttpRetry
Version: 0.1.0
Summary: 本项目提供了一个异步请求重试机制，旨在处理网络请求中的失败情况。通过使用装饰器，可以轻松地为异步函数添加重试逻辑，以确保在请求失败时能够自动重试，直到达到最大重试次数或成功为止。
License: MIT
Author: a木木
Author-email: mumuwj0001@163.com
Requires-Python: >=3.10
Classifier: License :: OSI Approved :: MIT License
Classifier: Programming Language :: Python :: 3
Classifier: Programming Language :: Python :: 3.10
Classifier: Programming Language :: Python :: 3.11
Classifier: Programming Language :: Python :: 3.12
Classifier: Programming Language :: Python :: 3.13
Requires-Dist: httpx (>=0.28.1,<0.29.0)
